<?xml version="1.0"?>
<ocs>
  <meta>
    <status>ok</status>
    <statuscode>100</statuscode>
    <message/>
  </meta>
  <data>
    <element>
      <id>115464</id>
      <share_type>6</share_type>
      <uid_owner>auser</uid_owner>
      <displayname_owner>A User</displayname_owner>
      <permissions>3</permissions>
      <stime>1481535991</stime>
      <parent/>
      <expiration/>
      <token>l5h8JYPb455oFkv</token>
      <uid_file_owner>auser</uid_file_owner>
      <displayname_file_owner>A User</displayname_file_owner>
      <path>/ownCloud Manual.pdf</path>
      <item_type>file</item_type>
      <mimetype>application/pdf</mimetype>
      <storage_id>home::auser</storage_id>
      <storage>993</storage>
      <item_source>3994491</item_source>
      <file_source>3994491</file_source>
      <file_parent>3994484</file_parent>
      <file_target></file_target>
      <share_with>user@example.com</share_with>
      <share_with_displayname>user@example.com</share_with_displayname>
      <name>ownCloud Manual</name>
      <mail_send>0</mail_send>
    </element>
  </data>
</ocs>
